uxf.py
uxf-2.8.1.data/scripts/uxfcompare.py
uxf-2.8.1.data/scripts/uxfconvert.py
uxf-2.8.1.data/scripts/uxflint.py
uxf-2.8.1.dist-info/LICENSE
uxf-2.8.1.dist-info/METADATA
uxf-2.8.1.dist-info/WHEEL
uxf-2.8.1.dist-info/top_level.txt
uxf-2.8.1.dist-info/RECORD
