Metadata-Version: 2.1
Name: uxf
Version: 2.8.1
Summary: A pure Python library supporting Uniform eXchange Format, a plain text human readable optionally typed storage format that supports custom types.
Home-page: https://github.com/mark-summerfield/uxf
Author: Mark Summerfield
Author-email: mark@qtrac.eu
License: GPLv3
Platform: UNKNOWN
Classifier: Development Status :: 5 - Production/Stable
Classifier: Intended Audience :: Developers
Classifier: License :: OSI Approved :: GNU General Public License v3 (GPLv3)
Classifier: Programming Language :: Python :: 3
Classifier: Programming Language :: Python :: 3.8
Classifier: Topic :: Software Development :: Libraries
Requires-Python: >=3.8
Requires-Dist: editabletuple
